disembedbuilder/__init__.py
disembedbuilder/disembedbuilder.py
disembedbuilder/preembeds.py
disembedbuilder-0.1.2.dist-info/LICENSE
disembedbuilder-0.1.2.dist-info/METADATA
disembedbuilder-0.1.2.dist-info/WHEEL
disembedbuilder-0.1.2.dist-info/top_level.txt
disembedbuilder-0.1.2.dist-info/RECORD
