Metadata-Version: 2.1
Name: disembedbuilder
Version: 0.1.2
Summary: Simple embed builder made with modals and buttons.
Home-page: https://github.com/Fadix47/disembedbuilder
Author: Fadix Meier
Author-email: fadix18123@gmail.com
Project-URL: Bug Tracker, https://github.com/Fadix47/disembedbuilder/issues
Classifier: Programming Language :: Python :: 3
Classifier: License :: OSI Approved :: MIT License
Classifier: Operating System :: OS Independent
Requires-Python: >=3.7
License-File: LICENSE
